odoo8_addon_web_widget_x2many_2d_matrix-8.0.1.1.0-py2.7-nspkg.pth
odoo_addons/web_widget_x2many_2d_matrix/__openerp__.py
odoo_addons/web_widget_x2many_2d_matrix/__init__.py
odoo_addons/web_widget_x2many_2d_matrix/README.rst
odoo_addons/web_widget_x2many_2d_matrix/i18n/it.po
odoo_addons/web_widget_x2many_2d_matrix/i18n/es.po
odoo_addons/web_widget_x2many_2d_matrix/i18n/ar.po
odoo_addons/web_widget_x2many_2d_matrix/i18n/tr.po
odoo_addons/web_widget_x2many_2d_matrix/i18n/hr.po
odoo_addons/web_widget_x2many_2d_matrix/i18n/sl.po
odoo_addons/web_widget_x2many_2d_matrix/i18n/de.po
odoo_addons/web_widget_x2many_2d_matrix/i18n/fr.po
odoo_addons/web_widget_x2many_2d_matrix/i18n/pt_BR.po
odoo_addons/web_widget_x2many_2d_matrix/i18n/fi.po
odoo_addons/web_widget_x2many_2d_matrix/views/templates.xml
odoo_addons/web_widget_x2many_2d_matrix/static/description/screenshot.png
odoo_addons/web_widget_x2many_2d_matrix/static/description/icon.png
odoo_addons/web_widget_x2many_2d_matrix/static/src/js/web_widget_x2many_2d_matrix.js
odoo_addons/web_widget_x2many_2d_matrix/static/src/css/web_widget_x2many_2d_matrix.css
odoo_addons/web_widget_x2many_2d_matrix/static/src/xml/web_widget_x2many_2d_matrix.xml
odoo8_addon_web_widget_x2many_2d_matrix-8.0.1.1.0.dist-info/top_level.txt
odoo8_addon_web_widget_x2many_2d_matrix-8.0.1.1.0.dist-info/WHEEL
odoo8_addon_web_widget_x2many_2d_matrix-8.0.1.1.0.dist-info/RECORD
odoo8_addon_web_widget_x2many_2d_matrix-8.0.1.1.0.dist-info/metadata.json
odoo8_addon_web_widget_x2many_2d_matrix-8.0.1.1.0.dist-info/DESCRIPTION.rst
odoo8_addon_web_widget_x2many_2d_matrix-8.0.1.1.0.dist-info/METADATA
odoo8_addon_web_widget_x2many_2d_matrix-8.0.1.1.0.dist-info/namespace_packages.txt
